fast_parse_time/__init__.py
fast_parse_time/api.py
fast_parse_time/core/__init__.py
fast_parse_time/explicit/bp/__init__.py
fast_parse_time/explicit/bp/explicit_time_extractor.py
fast_parse_time/explicit/dmo/__init__.py
fast_parse_time/explicit/dmo/day_month_validator.py
fast_parse_time/explicit/dmo/delimited_date_classifier.py
fast_parse_time/explicit/dto/__init__.py
fast_parse_time/explicit/svc/__init__.py
fast_parse_time/explicit/svc/classify_numeric_components.py
fast_parse_time/explicit/svc/preclassify_numeric_components.py
fast_parse_time/explicit/svc/tokenize_numeric_components.py
fast_parse_time/explicit/svc/validate_numeric_components.py
fast_parse_time/implicit/dmo/__init__.py
fast_parse_time/implicit/dmo/digit_text_replacer.py
fast_parse_time/implicit/dmo/keyword_sequence_extractor.py
fast_parse_time/implicit/dmo/keyword_sequence_filter.py
fast_parse_time/implicit/dmo/sequence_solution_finder.py
fast_parse_time/implicit/dto/__init__.py
fast_parse_time/implicit/dto/index_by_frame_kb.py
fast_parse_time/implicit/dto/index_by_keyterm_kb.py
fast_parse_time/implicit/dto/index_by_slot_kb.py
fast_parse_time/implicit/dto/keyterm_counter_kb.py
fast_parse_time/implicit/svc/__init__.py
fast_parse_time/implicit/svc/analyze_time_references.py
fast_parse_time/implicit/svc/resolve_time_references.py
fast_parse_time-1.2.0.dist-info/LICENSE
fast_parse_time-1.2.0.dist-info/METADATA
fast_parse_time-1.2.0.dist-info/WHEEL
fast_parse_time-1.2.0.dist-info/RECORD
