Metadata-Version: 2.1
Name: fast-parse-time
Version: 1.2.0
Summary: Natural Language (NLP) Extraction of Date and Time
Home-page: https://github.com/craigtrim/fast-parse-time
License: MIT
Keywords: date-parsing,time-parsing,date-extraction,nlp,natural-language,temporal-extraction,text-mining
Author: Craig Trim
Author-email: craigtrim@gmail.com
Maintainer: Craig Trim
Maintainer-email: craigtrim@gmail.com
Requires-Python: >=3.11.5,<4.0.0
Classifier: Development Status :: 5 - Production/Stable
Classifier: Intended Audience :: Developers
Classifier: License :: OSI Approved :: MIT License
Classifier: Natural Language :: English
Classifier: Operating System :: OS Independent
Classifier: Programming Language :: Python :: 3
Classifier: Programming Language :: Python :: 3.12
Classifier: Programming Language :: Python :: 3.11
Classifier: Topic :: Software Development :: Libraries :: Python Modules
Classifier: Topic :: Text Processing :: Linguistic
Classifier: Typing :: Typed
Requires-Dist: dateparser
Requires-Dist: word2number
Project-URL: Bug Tracker, https://github.com/craigtrim/fast-parse-time/issues
Project-URL: Repository, https://github.com/craigtrim/fast-parse-time
